autoforecast/__init__.py
autoforecast/automl.py
autoforecast/datasets/__init__.py
autoforecast/datasets/import_bitcoin_price.py
autoforecast/datasets/import_ml_db.py
autoforecast/datasets/tests/__init__.py
autoforecast/datasets/tests/import_bitcoin_price_test.py
autoforecast/datasets/tests/import_ml_db_test.py
autoforecast/examples/__init__.py
autoforecast/examples/autoforecast_bitcoin.py
autoforecast/examples/tests/__init__.py
autoforecast/examples/tests/autoforecast_bitcoin_test.py
autoforecast/metrics/__init__.py
autoforecast/metrics/metrics.py
autoforecast/metrics/tests/__init__.py
autoforecast/metrics/tests/metrics_test.py
autoforecast/models/__init__.py
autoforecast/models/hyperparameters.py
autoforecast/models/ml.py
autoforecast/models/models.py
autoforecast/models/naive.py
autoforecast/models/neural_net.py
autoforecast/models/pytorch_nnet.py
autoforecast/models/time_series.py
autoforecast/models/tests/__init__.py
autoforecast/models/tests/hyperparameters_test.py
autoforecast/models/tests/ml_test.py
autoforecast/models/tests/models_test.py
autoforecast/models/tests/naive_test.py
autoforecast/models/tests/neural_net_test.py
autoforecast/models/tests/pytorch_nnet_test.py
autoforecast/models/tests/time_series_test.py
autoforecast/preprocessing/__init__.py
autoforecast/preprocessing/categorical.py
autoforecast/preprocessing/engineering.py
autoforecast/preprocessing/features_selection.py
autoforecast/preprocessing/numerical.py
autoforecast/preprocessing/tests/__init__.py
autoforecast/preprocessing/tests/categorical_test.py
autoforecast/preprocessing/tests/engineering_test.py
autoforecast/preprocessing/tests/features_selection_test.py
autoforecast/preprocessing/tests/numerical_test.py
autoforecast/src/__init__.py
autoforecast/src/utils/__init__.py
autoforecast/src/utils/logger.py
autoforecast/src/utils/plot.py
autoforecast/src/utils/utils.py
autoforecast/src/utils/tests/__init__.py
autoforecast/src/utils/tests/logger_test.py
autoforecast-0.0.9.dist-info/LICENSE
autoforecast-0.0.9.dist-info/METADATA
autoforecast-0.0.9.dist-info/WHEEL
autoforecast-0.0.9.dist-info/top_level.txt
autoforecast-0.0.9.dist-info/RECORD
