Metadata-Version: 2.1
Name: autoforecast
Version: 0.0.9
Summary: AutoML time series forecasting
Home-page: https://github.com/GuillaumeSimo/autoforecast
Author: Guillaume Simo
Author-email: guillaume.simo@hotmail.fr
License: UNKNOWN
Platform: UNKNOWN
Classifier: Programming Language :: Python :: 3
Classifier: License :: OSI Approved :: MIT License
Classifier: Operating System :: OS Independent
Requires-Python: >=3.6
Requires-Dist: aiohttp (==3.7.4)
Requires-Dist: pystan (==2.19.1.1)
Requires-Dist: fbprophet (==0.7.1)
Requires-Dist: Keras (==2.4.3)
Requires-Dist: numpy (==1.19.4)
Requires-Dist: pandas (==1.2.0)
Requires-Dist: plotly (==5.1.0)
Requires-Dist: python-dotenv (==0.15.0)
Requires-Dist: scikit-optimize (==0.8.1)
Requires-Dist: scikit-learn (==0.24.0)
Requires-Dist: statsmodels (==0.12.1)
Requires-Dist: tensorflow (==2.4.2)
Requires-Dist: torch (==1.7.1)
Requires-Dist: xgboost (==1.3.1)
